cellmap_models/__init__.py
cellmap_models/utils.py
cellmap_models/pytorch/__init__.py
cellmap_models/pytorch/cellpose/__init__.py
cellmap_models/pytorch/cellpose/add_model.py
cellmap_models/pytorch/cellpose/download_checkpoint.py
cellmap_models/pytorch/cellpose/get_model.py
cellmap_models/pytorch/cellpose/load_model.py
cellmap_models/pytorch/cosem/__init__.py
cellmap_models/pytorch/cosem/download_checkpoint.py
cellmap_models/pytorch/cosem/load_model.py
cellmap_models/pytorch/cosem/setup04/__init__.py
cellmap_models/pytorch/cosem/setup04/model.py
cellmap_models/pytorch/cosem/setup26_1/__init__.py
cellmap_models/pytorch/cosem/setup26_1/model.py
cellmap_models/pytorch/cosem/setup28/__init__.py
cellmap_models/pytorch/cosem/setup28/model.py
cellmap_models/pytorch/cosem/setup36/__init__.py
cellmap_models/pytorch/cosem/setup36/model.py
cellmap_models/pytorch/cosem/setup45/__init__.py
cellmap_models/pytorch/cosem/setup45/model.py
cellmap_models/pytorch/untrained_models/__init__.py
cellmap_models/pytorch/untrained_models/resnet.py
cellmap_models/pytorch/untrained_models/unet_2D.py
cellmap_models/pytorch/untrained_models/unet_3D.py
cellmap_models/pytorch/untrained_models/vitnet.py
cellmap_models-0.1.3.dist-info/LICENSE
cellmap_models-0.1.3.dist-info/METADATA
cellmap_models-0.1.3.dist-info/WHEEL
cellmap_models-0.1.3.dist-info/entry_points.txt
cellmap_models-0.1.3.dist-info/top_level.txt
cellmap_models-0.1.3.dist-info/RECORD
