Metadata-Version: 2.2
Name: cellmap-models
Version: 0.1.3
Summary: Repository of model architectures and network weights used for CellMap segmentations.
Author-email: Jeff Rhoades <rhoadesj@hhmi.org>
License: BSD 3-Clause License
Project-URL: homepage, https://janelia-cellmap.github.io/cellmap-models
Project-URL: repository, https://github.com/janelia-cellmap/cellmap-models
Keywords: machine learning,deep learning,cell segmentation,cellpose,cellmap
Classifier: Programming Language :: Python :: 3
Requires-Python: >=3.7
License-File: LICENSE
Requires-Dist: torch
Requires-Dist: torchvision
Requires-Dist: numpy
Requires-Dist: tqdm
Requires-Dist: cellpose
Requires-Dist: ml-collections
Provides-Extra: dev
Requires-Dist: pytest; extra == "dev"
Requires-Dist: pytest-cov; extra == "dev"
Requires-Dist: pytest-mock; extra == "dev"
Requires-Dist: black; extra == "dev"
Requires-Dist: mypy; extra == "dev"
Requires-Dist: pdoc; extra == "dev"
Requires-Dist: pre-commit; extra == "dev"
Provides-Extra: pretrained
Requires-Dist: cellpose[gui]; extra == "pretrained"
Provides-Extra: all
Requires-Dist: cellmap-models[dev,pretrained]; extra == "all"
